LICENSE
MANIFEST.in
README.md
requirements.txt
setup.py
onnx2keras/__init__.py
onnx2keras/activation_layers.py
onnx2keras/constant_layers.py
onnx2keras/converter.py
onnx2keras/convolution_layers.py
onnx2keras/elementwise_layers.py
onnx2keras/layers.py
onnx2keras/linear_layers.py
onnx2keras/normalization_layers.py
onnx2keras/operation_layers.py
onnx2keras/padding_layers.py
onnx2keras/pooling_layers.py
onnx2keras/reshape_layers.py
onnx2keras/upsampling_layers.py
onnx2keras/utils.py
onnx2keras.egg-info/PKG-INFO
onnx2keras.egg-info/SOURCES.txt
onnx2keras.egg-info/dependency_links.txt
onnx2keras.egg-info/not-zip-safe
onnx2keras.egg-info/requires.txt
onnx2keras.egg-info/top_level.txt